rippy/Contracts.py
rippy/Distributions.py
rippy/FrequencySeverity.py
rippy/__init__.py
rippy/config.py
rippy/stats.py
rippy-0.0.8.dist-info/LICENSE
rippy-0.0.8.dist-info/METADATA
rippy-0.0.8.dist-info/WHEEL
rippy-0.0.8.dist-info/top_level.txt
rippy-0.0.8.dist-info/RECORD
