Metadata-Version: 2.1
Name: rippy
Version: 0.0.8
Summary: Reinsurance Pricing in Python!
Author: James Norman
Author-email: James Norman <james.norman@proteusllp.com>
License: MIT License
Project-URL: Homepage, https://github.com/ProteusLLP/rippy
Project-URL: Issues, https://github.com/ProteusLLP/rippy/issues
Keywords: reinsurance,actuarial,insurance
Classifier: Programming Language :: Python :: 3
Classifier: License :: OSI Approved :: MIT License
Classifier: Operating System :: OS Independent
Requires-Python: >=3.10
License-File: LICENSE
Requires-Dist: numpy
Requires-Dist: scipy
Provides-Extra: gpu
Requires-Dist: cupy-cuda11x ; extra == 'gpu'
